{
  "parent": "umbrellas:adventure/get_umbrella",
  "criteria": {
    "has_wind_catching_umbrella": {
      "conditions": {
        "items": [
          {
            "enchantments": [
              {
                "enchantment": "umbrellas:wind_catching"
              }
            ]
          }
        ]
      },
      "trigger": "minecraft:inventory_changed"
    }
  },
  "display": {
    "announce_to_chat": true,
    "description": {
      "translate": "advancements.umbrellas.get_wind_catching_umbrella.desc"
    },
    "frame": "task",
    "hidden": false,
    "icon": {
      "item": "umbrellas:umbrella",
      "nbt": "{Damage:0,Enchantments:[{id:\"umbrellas:gliding\",lvl:3s}]}"
    },
    "show_toast": true,
    "title": {
      "translate": "advancements.umbrellas.get_wind_catching_umbrella.name"
    }
  },
  "requirements": [
    [
      "has_wind_catching_umbrella"
    ]
  ],
  "sends_telemetry_event": true
}